uno_utils/__init__.py
uno_utils/_base.py
uno_utils/_range.py
uno_utils/_thread.py
uno_utils/_utils.py
uno_utils-0.2.0.dist-info/LICENSE
uno_utils-0.2.0.dist-info/METADATA
uno_utils-0.2.0.dist-info/WHEEL
uno_utils-0.2.0.dist-info/top_level.txt
uno_utils-0.2.0.dist-info/RECORD
